[
  {"url": "/news/press-releases/jl10051", "hugo_title": "FILE_NOT_FOUND", "drupal_title": "", "title_match": false},
  {"url": "/news/press-releases/hp502", "hugo_title": "FILE_NOT_FOUND", "drupal_title": "", "title_match": false},
  {"url": "/news/press-releases/tg1542", "hugo_title": "FILE_NOT_FOUND", "drupal_title": "", "title_match": false},
  {"url": "/news/press-releases/jy1291", "hugo_title": "FILE_NOT_FOUND", "drupal_title": "", "title_match": false},
  {"url": "/news/press-releases/200541314214215168", "hugo_title": "FILE_NOT_FOUND", "drupal_title": "", "title_match": false},
  {"url": "/news/press-releases/pr100897", "hugo_title": "FILE_NOT_FOUND", "drupal_title": "", "title_match": false},
  {"url": "/news/press-releases/jl0437", "hugo_title": "FILE_NOT_FOUND", "drupal_title": "", "title_match": false},
  {"url": "/news/press-releases/jy0140", "hugo_title": "FILE_NOT_FOUND", "drupal_title": "", "title_match": false},
  {"url": "/news/press-releases/20028141225012723", "hugo_title": "FILE_NOT_FOUND", "drupal_title": "", "title_match": false},
  {"url": "/news/press-releases/js2726", "hugo_title": "FILE_NOT_FOUND", "drupal_title": "", "title_match": false},
  {"url": "/news/press-releases/sm533", "hugo_title": "FILE_NOT_FOUND", "drupal_title": "", "title_match": false},
  {"url": "/news/press-releases/js2275", "hugo_title": "FILE_NOT_FOUND", "drupal_title": "", "title_match": false},
  {"url": "/news/press-releases/jy1671", "hugo_title": "FILE_NOT_FOUND", "drupal_title": "", "title_match": false},
  {"url": "/news/press-releases/js2252", "hugo_title": "FILE_NOT_FOUND", "drupal_title": "", "title_match": false},
  {"url": "/news/press-releases/jl0532", "hugo_title": "FILE_NOT_FOUND", "drupal_title": "", "title_match": false},
  {"url": "/news/press-releases/200991711403227291", "hugo_title": "FILE_NOT_FOUND", "drupal_title": "", "title_match": false},
  {"url": "/news/press-releases/jy0779", "hugo_title": "FILE_NOT_FOUND", "drupal_title": "", "title_match": false},
  {"url": "/news/press-releases/js2149", "hugo_title": "FILE_NOT_FOUND", "drupal_title": "", "title_match": false},
  {"url": "/news/press-releases/tg216", "hugo_title": "FILE_NOT_FOUND", "drupal_title": "", "title_match": false},
  {"url": "/news/press-releases/rr2278", "hugo_title": "FILE_NOT_FOUND", "drupal_title": "", "title_match": false},
  {"url": "/news/press-releases/po1090", "hugo_title": "FILE_NOT_FOUND", "drupal_title": "", "title_match": false},
  {"url": "/news/press-releases/tg253", "hugo_title": "FILE_NOT_FOUND", "drupal_title": "", "title_match": false},
  {"url": "/news/press-releases/po1001", "hugo_title": "FILE_NOT_FOUND", "drupal_title": "", "title_match": false},
  {"url": "/news/press-releases/2002930214479428", "hugo_title": "FILE_NOT_FOUND", "drupal_title": "", "title_match": false},
  {"url": "/news/press-releases/tg1336", "hugo_title": "FILE_NOT_FOUND", "drupal_title": "", "title_match": false},
  {"url": "/news/press-releases/hp836", "hugo_title": "FILE_NOT_FOUND", "drupal_title": "", "title_match": false},
  {"url": "/news/press-releases/jy1444", "hugo_title": "FILE_NOT_FOUND", "drupal_title": "", "title_match": false},
  {"url": "/news/press-releases/po3187", "hugo_title": "FILE_NOT_FOUND", "drupal_title": "", "title_match": false},
  {"url": "/news/press-releases/2007378455225140", "hugo_title": "FILE_NOT_FOUND", "drupal_title": "", "title_match": false},
  {"url": "/news/press-releases/js2425", "hugo_title": "FILE_NOT_FOUND", "drupal_title": "", "title_match": false},
  {"url": "/news/press-releases/js2015", "hugo_title": "FILE_NOT_FOUND", "drupal_title": "", "title_match": false},
  {"url": "/news/press-releases/tg665", "hugo_title": "FILE_NOT_FOUND", "drupal_title": "", "title_match": false},
  {"url": "/news/press-releases/tg653", "hugo_title": "FILE_NOT_FOUND", "drupal_title": "", "title_match": false},
  {"url": "/news/press-releases/tg1318", "hugo_title": "FILE_NOT_FOUND", "drupal_title": "", "title_match": false},
  {"url": "/news/press-releases/jl1956", "hugo_title": "FILE_NOT_FOUND", "drupal_title": "", "title_match": false},
  {"url": "/news/press-releases/jy0748", "hugo_title": "FILE_NOT_FOUND", "drupal_title": "", "title_match": false},
  {"url": "/news/press-releases/rr1859", "hugo_title": "FILE_NOT_FOUND", "drupal_title": "", "title_match": false},
  {"url": "/news/press-releases/hp646", "hugo_title": "FILE_NOT_FOUND", "drupal_title": "", "title_match": false},
  {"url": "/news/press-releases/jl0544", "hugo_title": "FILE_NOT_FOUND", "drupal_title": "", "title_match": false},
  {"url": "/news/press-releases/js2620", "hugo_title": "FILE_NOT_FOUND", "drupal_title": "", "title_match": false},
  {"url": "/news/press-releases/jl2361", "hugo_title": "FILE_NOT_FOUND", "drupal_title": "", "title_match": false},
  {"url": "/news/press-releases/rr2083", "hugo_title": "FILE_NOT_FOUND", "drupal_title": "", "title_match": false},
  {"url": "/news/press-releases/js676", "hugo_title": "FILE_NOT_FOUND", "drupal_title": "", "title_match": false},
  {"url": "/news/press-releases/jy1507", "hugo_title": "FILE_NOT_FOUND", "drupal_title": "", "title_match": false},
  {"url": "/news/press-releases/hp1070", "hugo_title": "FILE_NOT_FOUND", "drupal_title": "", "title_match": false},
  {"url": "/news/press-releases/200592914311622229", "hugo_title": "FILE_NOT_FOUND", "drupal_title": "", "title_match": false},
  {"url": "/news/press-releases/po2011", "hugo_title": "FILE_NOT_FOUND", "drupal_title": "", "title_match": false},
  {"url": "/news/press-releases/jy2732", "hugo_title": "FILE_NOT_FOUND", "drupal_title": "", "title_match": false},
  {"url": "/news/press-releases/rr2154", "hugo_title": "FILE_NOT_FOUND", "drupal_title": "", "title_match": false},
  {"url": "/news/press-releases/jl2150", "hugo_title": "FILE_NOT_FOUND", "drupal_title": "", "title_match": false},
  {"url": "/news/press-releases/tg1449", "hugo_title": "FILE_NOT_FOUND", "drupal_title": "", "title_match": false},
  {"url": "/news/press-releases/jy0866", "hugo_title": "FILE_NOT_FOUND", "drupal_title": "", "title_match": false},
  {"url": "/news/press-releases/jy2605", "hugo_title": "FILE_NOT_FOUND", "drupal_title": "", "title_match": false},
  {"url": "/news/press-releases/js4274", "hugo_title": "FILE_NOT_FOUND", "drupal_title": "", "title_match": false},
  {"url": "/news/press-releases/js2155", "hugo_title": "FILE_NOT_FOUND", "drupal_title": "", "title_match": false},
  {"url": "/news/press-releases/2005639474626898", "hugo_title": "FILE_NOT_FOUND", "drupal_title": "", "title_match": false},
  {"url": "/news/press-releases/tg157", "hugo_title": "FILE_NOT_FOUND", "drupal_title": "", "title_match": false},
  {"url": "/news/press-releases/rr3021", "hugo_title": "FILE_NOT_FOUND", "drupal_title": "", "title_match": false},
  {"url": "/news/press-releases/sm1030", "hugo_title": "FILE_NOT_FOUND", "drupal_title": "", "title_match": false},
  {"url": "/news/press-releases/20051130953326293", "hugo_title": "FILE_NOT_FOUND", "drupal_title": "", "title_match": false},
  {"url": "/news/press-releases/tg16", "hugo_title": "FILE_NOT_FOUND", "drupal_title": "", "title_match": false},
  {"url": "/news/press-releases/jl0561", "hugo_title": "FILE_NOT_FOUND", "drupal_title": "", "title_match": false},
  {"url": "/news/press-releases/jy0718", "hugo_title": "FILE_NOT_FOUND", "drupal_title": "", "title_match": false},
  {"url": "/news/press-releases/js3035", "hugo_title": "FILE_NOT_FOUND", "drupal_title": "", "title_match": false},
  {"url": "/news/press-releases/js3094", "hugo_title": "FILE_NOT_FOUND", "drupal_title": "", "title_match": false},
  {"url": "/news/press-releases/js1179", "hugo_title": "FILE_NOT_FOUND", "drupal_title": "", "title_match": false},
  {"url": "/news/press-releases/report3106", "hugo_title": "FILE_NOT_FOUND", "drupal_title": "", "title_match": false},
  {"url": "/news/press-releases/hp08", "hugo_title": "FILE_NOT_FOUND", "drupal_title": "", "title_match": false},
  {"url": "/news/press-releases/sm473", "hugo_title": "FILE_NOT_FOUND", "drupal_title": "", "title_match": false},
  {"url": "/news/press-releases/ls583", "hugo_title": "FILE_NOT_FOUND", "drupal_title": "", "title_match": false},
  {"url": "/news/press-releases/ls97", "hugo_title": "FILE_NOT_FOUND", "drupal_title": "", "title_match": false},
  {"url": "/news/press-releases/tg774", "hugo_title": "FILE_NOT_FOUND", "drupal_title": "", "title_match": false},
  {"url": "/news/press-releases/sm0203", "hugo_title": "FILE_NOT_FOUND", "drupal_title": "", "title_match": false},
  {"url": "/news/press-releases/jl0514", "hugo_title": "FILE_NOT_FOUND", "drupal_title": "", "title_match": false},
  {"url": "/news/press-releases/ls844", "hugo_title": "FILE_NOT_FOUND", "drupal_title": "", "title_match": false},
  {"url": "/news/press-releases/tg450", "hugo_title": "FILE_NOT_FOUND", "drupal_title": "", "title_match": false},
  {"url": "/news/press-releases/jy1086", "hugo_title": "FILE_NOT_FOUND", "drupal_title": "", "title_match": false},
  {"url": "/news/press-releases/200810716521117651", "hugo_title": "FILE_NOT_FOUND", "drupal_title": "", "title_match": false},
  {"url": "/news/press-releases/rr2767", "hugo_title": "FILE_NOT_FOUND", "drupal_title": "", "title_match": false},
  {"url": "/news/press-releases/ls737", "hugo_title": "FILE_NOT_FOUND", "drupal_title": "", "title_match": false},
  {"url": "/news/press-releases/po1086", "hugo_title": "FILE_NOT_FOUND", "drupal_title": "", "title_match": false},
  {"url": "/news/press-releases/2005102612756884", "hugo_title": "FILE_NOT_FOUND", "drupal_title": "", "title_match": false},
  {"url": "/news/press-releases/sm1017", "hugo_title": "FILE_NOT_FOUND", "drupal_title": "", "title_match": false},
  {"url": "/news/press-releases/js2329", "hugo_title": "FILE_NOT_FOUND", "drupal_title": "", "title_match": false},
  {"url": "/news/press-releases/hp131", "hugo_title": "FILE_NOT_FOUND", "drupal_title": "", "title_match": false},
  {"url": "/news/press-releases/sb0135", "hugo_title": "FILE_NOT_FOUND", "drupal_title": "", "title_match": false},
  {"url": "/news/press-releases/sm920", "hugo_title": "FILE_NOT_FOUND", "drupal_title": "", "title_match": false},
  {"url": "/news/press-releases/js1149", "hugo_title": "FILE_NOT_FOUND", "drupal_title": "", "title_match": false},
  {"url": "/news/press-releases/hp260", "hugo_title": "FILE_NOT_FOUND", "drupal_title": "", "title_match": false},
  {"url": "/news/press-releases/jy2462", "hugo_title": "FILE_NOT_FOUND", "drupal_title": "", "title_match": false},
  {"url": "/news/press-releases/jl9747", "hugo_title": "FILE_NOT_FOUND", "drupal_title": "", "title_match": false},
  {"url": "/news/press-releases/jl2425", "hugo_title": "FILE_NOT_FOUND", "drupal_title": "", "title_match": false},
  {"url": "/news/press-releases/20031215170237138", "hugo_title": "FILE_NOT_FOUND", "drupal_title": "", "title_match": false},
  {"url": "/news/press-releases/hp679", "hugo_title": "FILE_NOT_FOUND", "drupal_title": "", "title_match": false},
  {"url": "/news/press-releases/po3355", "hugo_title": "FILE_NOT_FOUND", "drupal_title": "", "title_match": false},
  {"url": "/news/press-releases/tg282", "hugo_title": "FILE_NOT_FOUND", "drupal_title": "", "title_match": false},
  {"url": "/news/press-releases/js1155", "hugo_title": "FILE_NOT_FOUND", "drupal_title": "", "title_match": false},
  {"url": "/news/press-releases/ls550", "hugo_title": "FILE_NOT_FOUND", "drupal_title": "", "title_match": false},
  {"url": "/news/press-releases/rr2464", "hugo_title": "FILE_NOT_FOUND", "drupal_title": "", "title_match": false},
  {"url": "/news/press-releases/jy2048", "hugo_title": "FILE_NOT_FOUND", "drupal_title": "", "title_match": false}
]
